addtwo/__init__.py
addtwo/core.py
addtwo_monu-0.1.3.dist-info/licenses/LICENSE
addtwo_monu-0.1.3.dist-info/METADATA
addtwo_monu-0.1.3.dist-info/WHEEL
addtwo_monu-0.1.3.dist-info/entry_points.txt
addtwo_monu-0.1.3.dist-info/top_level.txt
addtwo_monu-0.1.3.dist-info/RECORD
