Metadata-Version: 2.4
Name: addtwo-Monu
Version: 0.1.3
Summary: Tiny package that adds two numbers
Author-email: Monu <you@example.com>
License: MIT
Requires-Python: >=3.8
License-File: LICENSE
Dynamic: license-file
